FtApi/FtApi.py
FtApi/__init__.py
FtApi-2.2.3.dist-info/LICENSE.txt
FtApi-2.2.3.dist-info/METADATA
FtApi-2.2.3.dist-info/WHEEL
FtApi-2.2.3.dist-info/top_level.txt
FtApi-2.2.3.dist-info/RECORD
