Metadata-Version: 2.1
Name: FtApi
Version: 2.2.3
Summary: Class for manipulating 42 Api
Home-page: https://github.com/ryaoi/ftApi
Author: ryaoi
Author-email: nop@42.codes
License: LICENSE.txt
Platform: UNKNOWN
Requires-Dist: certifi (>=2019.6.16)
Requires-Dist: chardet (>=3.0.4)
Requires-Dist: idna (>=2.8)
Requires-Dist: Pygments (>=2.4.2)
Requires-Dist: requests (>=2.22.0)
Requires-Dist: urllib3 (>=1.26.5)
